COPYING
INSTALL
MANIFEST.in
feedvalidator.py
feedvalidator_googletransit.py
kmlparser.py
kmlwriter.py
location_editor.py
merge.py
schedule_viewer.py
setup.py
shape_importer.py
unusual_trip_filter.py
examples/filter_unused_stops.py
examples/google_random_queries.py
examples/shuttle_from_xmlfeed.py
examples/shuttle_from_xmlfeed.xml
examples/small_builder.py
examples/table.py
examples/table.txt
extensions/README
extensions/__init__.py
extensions/googletransit/README
extensions/googletransit/__init__.py
extensions/googletransit/agency.py
extensions/googletransit/extension_util.py
extensions/googletransit/fareattribute.py
extensions/googletransit/route.py
extensions/googletransit/setup_extension.py
extensions/googletransit/stop.py
extensions/googletransit/pybcp47/__init__.py
extensions/googletransit/pybcp47/bcp47languageparser.py
extensions/googletransit/pybcp47/language-subtag-registry.txt
extensions/googletransit/pybcp47/testpybcp47.py
extensions/googletransit/pybcp47/testdata/not-well-formed-tags.txt
extensions/googletransit/pybcp47/testdata/valid-tags.txt
extensions/googletransit/pybcp47/testdata/well-formed-not-valid-tags.txt
gtfsscheduleviewer/__init__.py
gtfsscheduleviewer/marey_graph.py
gtfsscheduleviewer/files/calendarpopup.js
gtfsscheduleviewer/files/index.html
gtfsscheduleviewer/files/index.js
gtfsscheduleviewer/files/labeled_marker.js
gtfsscheduleviewer/files/markerwithlabel.js
gtfsscheduleviewer/files/mm_20_blue.png
gtfsscheduleviewer/files/mm_20_blue_trans.png
gtfsscheduleviewer/files/mm_20_red_trans.png
gtfsscheduleviewer/files/mm_20_shadow.png
gtfsscheduleviewer/files/mm_20_shadow_trans.png
gtfsscheduleviewer/files/mm_20_yellow.png
gtfsscheduleviewer/files/style.css
gtfsscheduleviewer/files/svgcheck.vbs
tests/__init__.py
tests/testexamples.py
tests/testfeedvalidator.py
tests/testgoogletransitextension.py
tests/testkmlparser.py
tests/testkmlwriter.py
tests/testmerge.py
tests/testshapelib.py
tests/testunusual_trip_filter.py
tests/util.py
transitfeed.egg-info/PKG-INFO
transitfeed.egg-info/SOURCES.txt
transitfeed.egg-info/dependency_links.txt
transitfeed.egg-info/not-zip-safe
transitfeed.egg-info/top_level.txt