Metadata-Version: 1.1
Name: transitfeed
Version: 1.2.16
Summary: GTFS library and tools
Home-page: https://github.com/google/transitfeed/
Author: Multiple
Author-email: transitfeed@googlegroups.com
License: Apache License, Version 2.0
Download-URL: https://github.com/google/transitfeed/archive/1.2.16.tar.gz
Platform: OS Independent
Classifier: Development Status :: 4 - Beta
Classifier: Intended Audience :: Developers
Classifier: Intended Audience :: Information Technology
Classifier: Intended Audience :: Other Audience
Classifier: License :: OSI Approved :: Apache Software License
Classifier: Operating System :: OS Independent
Classifier: Programming Language :: Python
Classifier: Topic :: Scientific/Engineering :: GIS
Classifier: Topic :: Software Development :: Libraries :: Python Modules
